pytesmo/__init__.py
pytesmo/cdf_matching.py
pytesmo/df_metrics.py
pytesmo/scaling.py
pytesmo/temporal_matching.py
pytesmo/utils.py
pytesmo/colormaps/SWI_ASCAT.cmap
pytesmo/colormaps/__init__.py
pytesmo/colormaps/load_cmap.py
pytesmo/grid/__init__.py
pytesmo/grid/resample.py
pytesmo/interpolate/dctpls.py
pytesmo/metrics/__init__.py
pytesmo/metrics/_fast.c
pytesmo/metrics/_fast.cpython-312-i386-linux-gnu.so
pytesmo/metrics/_fast.pyx
pytesmo/metrics/_fast_pairwise.c
pytesmo/metrics/_fast_pairwise.cpython-312-i386-linux-gnu.so
pytesmo/metrics/_fast_pairwise.pyx
pytesmo/metrics/confidence_intervals.py
pytesmo/metrics/deprecated.py
pytesmo/metrics/pairwise.py
pytesmo/metrics/tcol.py
pytesmo/time_series/__init__.py
pytesmo/time_series/anomaly.py
pytesmo/time_series/filtering.py
pytesmo/time_series/filters.c
pytesmo/time_series/filters.cpython-312-i386-linux-gnu.so
pytesmo/time_series/filters.pyx
pytesmo/time_series/grouping.py
pytesmo/timedate/__init__.py
pytesmo/timedate/dekad.py
pytesmo/timedate/julian.py
pytesmo/validation_framework/__init__.py
pytesmo/validation_framework/adapters.py
pytesmo/validation_framework/data_manager.py
pytesmo/validation_framework/data_scalers.py
pytesmo/validation_framework/error_handling.py
pytesmo/validation_framework/metric_calculators.py
pytesmo/validation_framework/metric_calculators_adapters.py
pytesmo/validation_framework/results_manager.py
pytesmo/validation_framework/start_validation.py
pytesmo/validation_framework/temporal_matchers.py
pytesmo/validation_framework/upscaling.py
pytesmo/validation_framework/validation.py
pytesmo-0.18.0.dist-info/AUTHORS.rst
pytesmo-0.18.0.dist-info/LICENSE.txt
pytesmo-0.18.0.dist-info/METADATA
pytesmo-0.18.0.dist-info/WHEEL
pytesmo-0.18.0.dist-info/top_level.txt
pytesmo-0.18.0.dist-info/RECORD
