Metadata-Version: 2.2
Name: pytesmo
Version: 0.18.0
Summary: Python Toolbox for the evaluation of soil moisture observations
Home-page: https://www.geo.tuwien.ac.at/
Author: TU Wien
Author-email: support@qa4sm.eu
License: mit
Project-URL: Documentation, https://pytesmo.readthedocs.io/
Platform: any
Classifier: Development Status :: 4 - Beta
Classifier: Programming Language :: Python
Requires-Python: >=3.9
License-File: LICENSE.txt
License-File: AUTHORS.rst
Requires-Dist: importlib-metadata; python_version < "3.8"
Requires-Dist: numpy>=2.0
Requires-Dist: numba
Requires-Dist: scipy>=0.12
Requires-Dist: pandas>=0.23.0
Requires-Dist: netCDF4!=1.6.2,>=1.0.1
Requires-Dist: pygeogrids
Requires-Dist: pygeobase>=0.6.0
Requires-Dist: pynetcf>=0.4.0
Requires-Dist: configparser
Requires-Dist: pykdtree
Requires-Dist: repurpose>=0.13.1
Requires-Dist: cadati>=0.0.2
Requires-Dist: Cython>=0.29.21
Requires-Dist: scikit-learn
Provides-Extra: testing
Requires-Dist: ascat==2.4.3; extra == "testing"
Requires-Dist: ismn==1.5.1; extra == "testing"
Requires-Dist: nbconvert; extra == "testing"
Requires-Dist: ipykernel; extra == "testing"
Requires-Dist: sphinx_rtd_theme; extra == "testing"
Requires-Dist: matplotlib; extra == "testing"
Requires-Dist: pytest; extra == "testing"
Requires-Dist: pytest-cov; extra == "testing"
Requires-Dist: pytest-mpl; extra == "testing"
Requires-Dist: pre-commit; extra == "testing"
Requires-Dist: flake8; extra == "testing"
Requires-Dist: yapf; extra == "testing"
